perusatproc/__init__.py
perusatproc/calibration.py
perusatproc/metadata.py
perusatproc/orthorectification.py
perusatproc/pansharpening.py
perusatproc/util.py
perusatproc/console/__init__.py
perusatproc/console/calibrate.py
perusatproc/console/orthorectify.py
perusatproc/console/pansharpen.py
perusatproc/console/process.py
perusatproc/data/egm96.grd
perusatproc/data/dem/S12W077.tif
perusatproc/data/dem/S12W078.tif
perusatproc/data/dem/S13W077.tif
perusatproc/data/dem/S13W078.tif
perusatproc-0.1.6.dist-info/AUTHORS.rst
perusatproc-0.1.6.dist-info/LICENSE.txt
perusatproc-0.1.6.dist-info/METADATA
perusatproc-0.1.6.dist-info/WHEEL
perusatproc-0.1.6.dist-info/entry_points.txt
perusatproc-0.1.6.dist-info/top_level.txt
perusatproc-0.1.6.dist-info/RECORD
