Metadata-Version: 2.1
Name: perusatproc
Version: 0.1.6
Summary: Process PeruSat-1 Level 2A scenes
Home-page: https://github.com/undp/perusatproc/
Author: Damián Silvani
Author-email: munshkr@gmail.com
License: mit
Project-URL: Documentation, https://pyscaffold.org/
Platform: any
Classifier: Development Status :: 4 - Beta
Classifier: Programming Language :: Python
Requires-Python: >=3.6
License-File: LICENSE.txt
License-File: AUTHORS.rst
Requires-Dist: rasterio
Requires-Dist: xmltodict
Requires-Dist: importlib-metadata ; python_version < "3.8"
Provides-Extra: testing
Requires-Dist: pytest ; extra == 'testing'
Requires-Dist: pytest-cov ; extra == 'testing'
